pycaldera/__init__.py
pycaldera/__meta__.py
pycaldera/async_client.py
pycaldera/client.py
pycaldera/const.py
pycaldera/exceptions.py
pycaldera/models.py
pycaldera-0.1.0.dist-info/LICENSE
pycaldera-0.1.0.dist-info/METADATA
pycaldera-0.1.0.dist-info/WHEEL
pycaldera-0.1.0.dist-info/top_level.txt
pycaldera-0.1.0.dist-info/RECORD
