Metadata-Version: 2.2
Name: pycaldera
Version: 0.1.0
Summary: Unofficial Python client for Caldera Spa API
Home-page: https://github.com/mwatson2/pycaldera
Author: Mark Watson
Author-email: markwatson@cantab.net
License: MIT
Classifier: Natural Language :: English
Classifier: Programming Language :: Python
Classifier: Programming Language :: Python :: 3
Classifier: Programming Language :: Python :: 3.8
Classifier: Programming Language :: Python :: 3.9
Classifier: Programming Language :: Python :: 3.10
Classifier: Programming Language :: Python :: 3.11
Classifier: Programming Language :: Python :: 3.12
Requires-Python: >=3.8
License-File: LICENSE
Requires-Dist: aiohttp>=3.8.0
Requires-Dist: black>=23.0.0
Requires-Dist: isort>=5.12.0
Requires-Dist: mypy>=1.0.0
Requires-Dist: pydantic>=2.0.0
Requires-Dist: pylint>=2.17.0
Requires-Dist: pytest>=7.0.0
Requires-Dist: pytest-aiohttp>=1.0.0
Requires-Dist: pytest-asyncio>=0.21.0
Requires-Dist: pytest-cov>=4.0.0
Provides-Extra: test
Requires-Dist: pytest; extra == "test"
Requires-Dist: pytest-cov; extra == "test"
Requires-Dist: pytest-flake8; extra == "test"
Provides-Extra: docs
Requires-Dist: myst-parser; extra == "docs"
Requires-Dist: pypandoc>=1.15; extra == "docs"
Requires-Dist: readthedocs-sphinx-search; python_version >= "3.6" and extra == "docs"
Requires-Dist: sphinx<6,>=3.5.4; extra == "docs"
Requires-Dist: sphinx-autobuild; extra == "docs"
Requires-Dist: sphinx_book_theme; extra == "docs"
Requires-Dist: watchdog<1.0.0; python_version < "3.6" and extra == "docs"
Provides-Extra: dev
Requires-Dist: black>=23.0.0; extra == "dev"
Requires-Dist: isort>=5.12.0; extra == "dev"
Requires-Dist: mypy>=1.0.0; extra == "dev"
Requires-Dist: pylint>=2.17.0; extra == "dev"
Requires-Dist: pytest>=7.0.0; extra == "dev"
Requires-Dist: pytest-aiohttp>=1.0.0; extra == "dev"
Requires-Dist: pytest-asyncio>=0.21.0; extra == "dev"
Requires-Dist: pytest-cov>=4.0.0; extra == "dev"
Provides-Extra: all
Requires-Dist: black>=23.0.0; extra == "all"
Requires-Dist: isort>=5.12.0; extra == "all"
Requires-Dist: mypy>=1.0.0; extra == "all"
Requires-Dist: myst-parser; extra == "all"
Requires-Dist: pylint>=2.17.0; extra == "all"
Requires-Dist: pypandoc>=1.15; extra == "all"
Requires-Dist: pytest; extra == "all"
Requires-Dist: pytest-aiohttp>=1.0.0; extra == "all"
Requires-Dist: pytest-asyncio>=0.21.0; extra == "all"
Requires-Dist: pytest-cov; extra == "all"
Requires-Dist: pytest-cov>=4.0.0; extra == "all"
Requires-Dist: pytest-flake8; extra == "all"
Requires-Dist: pytest>=7.0.0; extra == "all"
Requires-Dist: readthedocs-sphinx-search; python_version >= "3.6" and extra == "all"
Requires-Dist: sphinx-autobuild; extra == "all"
Requires-Dist: sphinx<6,>=3.5.4; extra == "all"
Requires-Dist: sphinx_book_theme; extra == "all"
Requires-Dist: watchdog<1.0.0; python_version < "3.6" and extra == "all"
Dynamic: author
Dynamic: author-email
Dynamic: classifier
Dynamic: description
Dynamic: description-content-type
Dynamic: home-page
Dynamic: license
Dynamic: provides-extra
Dynamic: requires-dist
Dynamic: requires-python
Dynamic: summary
